videolab_youtube_crawler/CATEGORY_US.json
videolab_youtube_crawler/ChannelCrawler.py
videolab_youtube_crawler/ChannelSearcher.py
videolab_youtube_crawler/CommentCrawler.py
videolab_youtube_crawler/CrawlerObject.py
videolab_youtube_crawler/SubtitleCrawler.py
videolab_youtube_crawler/US_CATE.json
videolab_youtube_crawler/VideoCrawler.py
videolab_youtube_crawler/VideoDownloader.py
videolab_youtube_crawler/VideoSearcher.py
videolab_youtube_crawler/__init__.py
videolab_youtube_crawler/tester.py
videolab_youtube_crawler-1.2.3.dist-info/LICENSE.txt
videolab_youtube_crawler-1.2.3.dist-info/METADATA
videolab_youtube_crawler-1.2.3.dist-info/WHEEL
videolab_youtube_crawler-1.2.3.dist-info/dependency_links.txt
videolab_youtube_crawler-1.2.3.dist-info/top_level.txt
videolab_youtube_crawler-1.2.3.dist-info/RECORD
